setuptools_pkg/__init__.py
setuptools_pkg/bdist_pkg.py
setuptools_pkg-0.9.dist-info/DESCRIPTION.rst
setuptools_pkg-0.9.dist-info/METADATA
setuptools_pkg-0.9.dist-info/RECORD
setuptools_pkg-0.9.dist-info/WHEEL
setuptools_pkg-0.9.dist-info/entry_points.txt
setuptools_pkg-0.9.dist-info/metadata.json
setuptools_pkg-0.9.dist-info/top_level.txt
